gameragui.py
GAMERA_gui-1.0.4.dist-info/LICENSE
GAMERA_gui-1.0.4.dist-info/METADATA
GAMERA_gui-1.0.4.dist-info/WHEEL
GAMERA_gui-1.0.4.dist-info/entry_points.txt
GAMERA_gui-1.0.4.dist-info/top_level.txt
GAMERA_gui-1.0.4.dist-info/RECORD
