Metadata-Version: 2.1
Name: GAMERA-gui
Version: 1.0.4
Summary: GAMERA MHD simulation GUI viewer
Home-page: https://github.com/devojyoti96/GAMERA-gui
Author: Devojyoti Kansabanik
Author-email: dkansabanik@ucar.edu
Classifier: Programming Language :: Python :: 3
Classifier: License :: OSI Approved :: MIT License
Classifier: Operating System :: OS Independent
Requires-Python: >=3.7
License-File: LICENSE
Requires-Dist: numpy
Requires-Dist: h5py
Requires-Dist: matplotlib
Requires-Dist: PyQt5
Requires-Dist: astropy
